IgaProTest/__init__.py
IgaProTest/some_module.py
IgaProTest/test.py
IgaProTest-0.3.0.dist-info/METADATA
IgaProTest-0.3.0.dist-info/WHEEL
IgaProTest-0.3.0.dist-info/top_level.txt
IgaProTest-0.3.0.dist-info/RECORD
