Metadata-Version: 2.1
Name: IgaProTest
Version: 0.3.0
Summary: FOR TEST!!!
Home-page: https://github.com/admin-iga/IgaProTest
Author: IGA-PRO (admin-iga)
Classifier: Programming Language :: Python :: 3
Classifier: License :: OSI Approved :: MIT License
Classifier: Operating System :: OS Independent
Requires-Python: >=3.6
